{
    "basic_info": {
      "page_title": "Davina Griss | Portfolio",
      "name": "Davina Griss",
      "titles": [ "Front-end Developer", "Senior Data Engineer", "Dev Team lead", "Mobile App Developer" ],
      "social": [
        {
          "name": "github",
          "url": "https://github.com",
          "class": "fab fa-github"
        },
        {
          "name": "instagram",
          "url": "https://www.instagram.com",
          "class": "fab fa-instagram"
        }
      ],
      "image": "myProfile.jpg"
    },
    "skills": {
      "icons": [
        {
          "name": "HTML 5",
          "class": "devicon-html5-plain"
        },
        {
          "name": "CSS 3",
          "class": "devicon-css3-plain"
        },
        {
          "name": "Angular",
          "class": "devicon-angularjs-plain"
        },
        {
          "name": "TypeScript",
          "class": "devicon-typescript-plain"
        },
        {
          "name": "JavaScript",
          "class": "devicon-javascript-plain"
        },
        {
          "name": "Sass",
          "class": "devicon-sass-original"
        },
        {
          "name": "Bootstrap",
          "class": "devicon-bootstrap-plain"
        },
        {
          "name": "C#",
          "class": "devicon-csharp-plain"
        },
        {
          "name": "MySql",
          "class": "devicon-mysql-plain"
        }
      ]
    },
    "projects": {
      "AnimalShelter": {
        "startDate": "2020",
        "images": [
          "images/portfolio/animal-shelter/p1.jpg",
          "images/portfolio/animal-shelter/p2.jpg"
        ],
        "url": "",
        "technologies": [
          {
            "class": "devicon-angularjs-plain",
            "name": "Angular"
          },
          {
            "class": "devicon-typescript-plain",
            "name": "TypeScript"
          },
          {
            "class": "devicon-csharp-plain",
            "name": "C#"
          }
        ]
      },
      "Photography": {
        "startDate": "2018",
        "images": [
          "images/portfolio/photography/p1.jpg",
          "images/portfolio/photography/p2.jpg"
        ],
        "url": "https://github.com",
        "technologies": [
          {
            "class": "devicon-react-original",
            "name": "React"
          },
          {
            "class": "devicon-javascript-plain",
            "name": "JavaScript"
          }
        ]
      },
      "ObjectViewer": {
        "startDate": "2015",
        "images": [
          "images/portfolio/adventure/p1.jpg",
          "images/portfolio/adventure/p2.jpg"
        ],
        "url": "https://github.com",
        "technologies": [
          {
            "class": "devicon-angularjs-plain",
            "name": "Angular"
          },
          {
            "class": "devicon-typescript-plain",
            "name": "TypeScript"
          },
          {
            "class": "devicon-csharp-plain",
            "name": "C#"
          }
        ]
      }
    },
    "experience":[
      {
        "company": "DefOpenSource",
        "title": "Front-End Developer",
        "years": "10.2019 - present",
        "mainTech": [
          "Angular 8/9/10"
        ],
        "technologies": [
          "REST API",
          "RxJS",
          "JavaScript",
          "Bootstrap",
          "MDBootstrap",
          "EF Core",
          ".NET Core",
          "SignalR",
          "Angular Material"
        ]
      },
      {
        "company": "Serros Solutions",
        "title": "Intern",
        "years": "01.2018 - 09.2019",
        "mainTech": [
          "Angular 7/8"
        ],
        "technologies": [
          "RxJS",
          "Django",
          "PHP",
          "JavaScript",
          "DHTMLX Gantt"
        ]
      }
    ],
    "languages":{
      "English": "twemoji:flag-for-flag-united-kingdom",
      "Polskie": "twemoji:flag-for-flag-poland"
    }
  }